{
  "batch_semantics": {
    "batch_hpo_semantics": "train.batch_size is the per-task effective batch size; total samples per update equals num_tasks * train.batch_size.",
    "configured_effective_batch_per_task": 8,
    "configured_effective_update_samples": 24,
    "device_transfer_semantics": "GPU staging chunks are only outer transport groups of whole logical micro-batches; they do not redefine vote partitioning or the effective update batch.",
    "gpu_streaming_chunk_size": 8,
    "logical_micro_batch_size": 4,
    "num_tasks_per_update": 3
  },
  "best_val_acc": 0.6580383140584511,
  "cli_overrides": [
    "model.backbone_backend=hf",
    "model.hf_load_pretrained=true",
    "model.backbone=deberta",
    "model.hf_pretrained_name=microsoft/deberta-v3-base",
    "seed=2",
    "method.name=ours",
    "train.steps=80",
    "train.eval_every_steps=50",
    "method.ours.use_load_norm=true",
    "method.ours.eps=6.040782662e-09",
    "method.ours.lambda_align=0.001112161582",
    "train.lr=4.857513492e-06"
  ],
  "config_path": "configs/multitask_glue3_rte_mrpc_cola_real.yaml",
  "config_path_resolved": "/share/home/yuli0398/Optimization/MOE-grad-conflict-routing/configs/multitask_glue3_rte_mrpc_cola_real.yaml",
  "data_reproducibility": {
    "data_source": "glue",
    "global_seed": 2,
    "loader_seed_base": 2035,
    "task_order": [
      "glue/rte",
      "glue/mrpc",
      "glue/cola"
    ],
    "tasks": {
      "glue/cola": {
        "num_labels": 2,
        "task": "glue/cola",
        "tokenizer_name": "microsoft/deberta-v3-base",
        "train_loader_shuffle_seed": 7300216,
        "train_size": 8551,
        "val_loader_shuffle_seed": 7300217,
        "val_size": 1043
      },
      "glue/mrpc": {
        "num_labels": 2,
        "task": "glue/mrpc",
        "tokenizer_name": "microsoft/deberta-v3-base",
        "train_loader_shuffle_seed": 7455845,
        "train_size": 3668,
        "val_loader_shuffle_seed": 7455846,
        "val_size": 408
      },
      "glue/rte": {
        "num_labels": 2,
        "task": "glue/rte",
        "tokenizer_name": "microsoft/deberta-v3-base",
        "train_loader_shuffle_seed": 6612172,
        "train_size": 2490,
        "val_loader_shuffle_seed": 6612173,
        "val_size": 277
      }
    }
  },
  "final_diagnostics": {
    "avg_intra_expert_coherence": 0.7375094213253112,
    "expert_diversity": [
      0.9779143013519783,
      0.9618756990690365,
      0.978458256816425,
      0.9426775326102006
    ],
    "expert_names": [
      "e0",
      "e1",
      "e2",
      "e3"
    ],
    "expert_purity": [
      0.4017578959465027,
      0.4475693702697754,
      0.39767593145370483,
      0.4773731827735901
    ],
    "inter_expert_similarity": -0.1511222170714902,
    "inter_expert_similarity_matrix": [
      [
        1.0,
        -0.5633227111965967,
        -0.2688337103914059,
        -0.185900774401287
      ],
      [
        -0.5633227111965967,
        1.0,
        0.14644733473894536,
        -0.11243807540802583
      ],
      [
        -0.2688337103914059,
        0.14644733473894536,
        1.0,
        0.07731463422942902
      ],
      [
        -0.185900774401287,
        -0.11243807540802583,
        0.07731463422942902,
        1.0
      ]
    ],
    "intra_expert_coherence": [
      0.7752513529890335,
      0.7401010500639611,
      0.5713552479187872,
      0.8633300343294629
    ],
    "overall_task_conflict_cos": 0.5649086208286928,
    "task_conflict_matrix": [
      [
        1.0,
        0.7739988819942692,
        0.458735530070181
      ],
      [
        0.7739988819942692,
        1.0,
        0.46199145042162804
      ],
      [
        0.458735530070181,
        0.46199145042162804,
        1.0
      ]
    ],
    "task_grad_norm_cv": 0.22430965680480547,
    "task_grad_norms": [
      7.06163215637207,
      9.0308198928833,
      5.141894817352295
    ],
    "task_names": [
      "glue/rte",
      "glue/mrpc",
      "glue/cola"
    ]
  },
  "final_step_metrics": {
    "alignment_reward": 0.24483849108219147,
    "avg_intra_expert_coherence": 0.7375094213253112,
    "expert_diversity_e0": 0.9779143013519783,
    "expert_diversity_e1": 0.9618756990690365,
    "expert_diversity_e2": 0.978458256816425,
    "expert_diversity_e3": 0.9426775326102006,
    "expert_diversity_mean": 0.96523144746191,
    "expert_purity_e0": 0.4017578959465027,
    "expert_purity_e1": 0.4475693702697754,
    "expert_purity_e2": 0.39767593145370483,
    "expert_purity_e3": 0.4773731827735901,
    "expert_purity_mean": 0.43109409511089325,
    "inter_expert_similarity": -0.1511222170714902,
    "inter_expert_similarity_e0_e0": 1.0,
    "inter_expert_similarity_e0_e1": -0.5633227111965967,
    "inter_expert_similarity_e0_e2": -0.2688337103914059,
    "inter_expert_similarity_e0_e3": -0.185900774401287,
    "inter_expert_similarity_e1_e0": -0.5633227111965967,
    "inter_expert_similarity_e1_e1": 1.0,
    "inter_expert_similarity_e1_e2": 0.14644733473894536,
    "inter_expert_similarity_e1_e3": -0.11243807540802583,
    "inter_expert_similarity_e2_e0": -0.2688337103914059,
    "inter_expert_similarity_e2_e1": 0.14644733473894536,
    "inter_expert_similarity_e2_e2": 1.0,
    "inter_expert_similarity_e2_e3": 0.07731463422942902,
    "inter_expert_similarity_e3_e0": -0.185900774401287,
    "inter_expert_similarity_e3_e1": -0.11243807540802583,
    "inter_expert_similarity_e3_e2": 0.07731463422942902,
    "inter_expert_similarity_e3_e3": 1.0,
    "intra_expert_coherence_e0": 0.7752513529890335,
    "intra_expert_coherence_e1": 0.7401010500639611,
    "intra_expert_coherence_e2": 0.5713552479187872,
    "intra_expert_coherence_e3": 0.8633300343294629,
    "l_conflict": -0.24483849108219147,
    "l_conflict_e0": -0.019385002553462982,
    "l_conflict_e1": -0.09496042877435684,
    "l_conflict_e2": -0.04162794351577759,
    "l_conflict_e3": -0.08886511623859406,
    "load_cv": 0.357326703390276,
    "load_max_min_ratio": 2.979668731608063,
    "overall_task_conflict_cos": 0.5649086208286928,
    "router_conflict_grad_l2": 0.0,
    "router_entropy": 1.2976528094322592,
    "router_load_e0": 0.122737817466259,
    "router_load_e1": 0.28944435715675354,
    "router_load_e2": 0.2220998853445053,
    "router_load_e3": 0.3657180368900299,
    "step": 80.0,
    "task_acc__glue_cola": 0.7085330776605945,
    "task_acc__glue_mrpc": 0.7132352941176471,
    "task_acc__glue_rte": 0.5523465703971119,
    "task_conflict_t0_t0": 1.0,
    "task_conflict_t0_t1": 0.7739988819942692,
    "task_conflict_t0_t2": 0.458735530070181,
    "task_conflict_t1_t0": 0.7739988819942692,
    "task_conflict_t1_t1": 1.0,
    "task_conflict_t1_t2": 0.46199145042162804,
    "task_conflict_t2_t0": 0.458735530070181,
    "task_conflict_t2_t1": 0.46199145042162804,
    "task_conflict_t2_t2": 1.0,
    "task_grad_norm_cv": 0.22430965680480547,
    "task_loss__glue_cola": 0.5458474141609577,
    "task_loss__glue_mrpc": 0.5503922306439456,
    "task_loss__glue_rte": 0.6945150218691145,
    "train_acc": 0.6571220716663241,
    "train_loss": 0.5934800439299274,
    "train_step_loss": 0.6290437082449596,
    "utilization_ratio": 0.75,
    "val_acc": 0.6580383140584511,
    "val_loss": 0.5969182222246726
  },
  "final_val_acc": 0.6580383140584511,
  "method": "ours",
  "num_eval_points": 2,
  "overhead": {
    "mean_train_step_time_sec": 0.30785716808750296,
    "peak_cuda_memory_mb": 3754.86572265625,
    "wall_time_sec": 138.513623544015
  },
  "reproducibility": {
    "command": "/share/home/yuli0398/Optimization/MOE-grad-conflict-routing/scripts/run.py --config configs/multitask_glue3_rte_mrpc_cola_real.yaml --set model.backbone_backend=hf --set model.hf_load_pretrained=true --set model.backbone=deberta --set model.hf_pretrained_name=microsoft/deberta-v3-base --set seed=2 --set method.name=ours --set train.steps=80 --set train.eval_every_steps=50 --set method.ours.use_load_norm=true --set method.ours.eps=6.040782662e-09 --set method.ours.lambda_align=0.001112161582 --set train.lr=4.857513492e-06 --out /share/home/yuli0398/Optimization/MOE-grad-conflict-routing/runs/paper_suite/multi_task/glue3_deberta/hpo/ours/trial_runs/coarse_076/ours_s2.json --curve_out /share/home/yuli0398/Optimization/MOE-grad-conflict-routing/runs/paper_suite/multi_task/glue3_deberta/hpo/ours/trial_runs/coarse_076/ours_s2_curve.csv",
    "curve_path": "/share/home/yuli0398/Optimization/MOE-grad-conflict-routing/runs/paper_suite/multi_task/glue3_deberta/hpo/ours/trial_runs/coarse_076/ours_s2_curve.csv",
    "cwd": "/share/home/yuli0398/Optimization/MOE-grad-conflict-routing",
    "runtime": {
      "cuda_available": true,
      "cuda_device_count": 1,
      "cuda_device_names": [
        "NVIDIA GeForce RTX 3090"
      ],
      "platform": "Linux-5.15.0-139-generic-x86_64-with-glibc2.31",
      "python_version": "3.10.18",
      "torch_version": "2.5.1+cu121"
    },
    "summary_path": "/share/home/yuli0398/Optimization/MOE-grad-conflict-routing/runs/paper_suite/multi_task/glue3_deberta/hpo/ours/trial_runs/coarse_076/ours_s2.json"
  },
  "resolved_config": {
    "data": {
      "datasets": [
        "glue/rte",
        "glue/mrpc",
        "glue/cola"
      ],
      "source": "glue",
      "train_size": 0,
      "val_size": 0
    },
    "method": {
      "baseline_cagrad": {
        "c": 0.4,
        "eps": 1e-08,
        "inner_lr": 0.1,
        "inner_steps": 10
      },
      "name": "ours",
      "ours": {
        "eps": 6.040782662e-09,
        "lambda_align": 0.001112161582,
        "micro_batch_size": 8,
        "use_load_norm": true
      }
    },
    "model": {
      "backbone": "deberta",
      "backbone_backend": "hf",
      "dropout": 0.1,
      "expert_type": "lora",
      "ffn_hidden_dim": 3072,
      "hf_load_pretrained": true,
      "hf_local_files_only": false,
      "hf_pretrained_name": "microsoft/deberta-v3-base",
      "hidden_dim": 768,
      "lora_alpha": 16.0,
      "lora_rank": 16,
      "max_seq_len": 128,
      "num_classes": 2,
      "num_experts": 4,
      "routing_mode": "softmax",
      "seq_len": 128,
      "top_k": 2,
      "vocab_size": 30522
    },
    "seed": 2,
    "train": {
      "batch_size": 8,
      "device_batch_size": 0,
      "eval_every_steps": 50,
      "eval_max_batches": 0,
      "grad_clip": 1.0,
      "log_every": 10,
      "lr": 4.857513492e-06,
      "micro_batch_size": 4,
      "steps": 80,
      "weight_decay": 0.01
    }
  },
  "resolved_config_sha256": "76feb17773730389a7e2007d42146d705c4e5714268d10a64a93863c62729a34",
  "seed": 2
}