{
  "batch_semantics": {
    "batch_hpo_semantics": "train.batch_size is the per-task effective batch size; total samples per update equals num_tasks * train.batch_size.",
    "configured_effective_batch_per_task": 8,
    "configured_effective_update_samples": 24,
    "device_transfer_semantics": "GPU staging chunks are only outer transport groups of whole logical micro-batches; they do not redefine vote partitioning or the effective update batch.",
    "gpu_streaming_chunk_size": 8,
    "logical_micro_batch_size": 4,
    "num_tasks_per_update": 3
  },
  "best_val_acc": 0.7065498810351235,
  "cli_overrides": [
    "model.backbone_backend=hf",
    "model.hf_load_pretrained=true",
    "model.backbone=deberta",
    "model.hf_pretrained_name=microsoft/deberta-v3-base",
    "seed=3",
    "method.name=ours",
    "train.steps=80",
    "train.eval_every_steps=50",
    "method.ours.use_load_norm=true",
    "method.ours.eps=1.744289893e-07",
    "method.ours.lambda_align=0.005242072127",
    "train.lr=2.699448611e-05"
  ],
  "config_path": "configs/multitask_glue3_rte_mrpc_cola_real.yaml",
  "config_path_resolved": "/share/home/yuli0398/Optimization/MOE-grad-conflict-routing/configs/multitask_glue3_rte_mrpc_cola_real.yaml",
  "data_reproducibility": {
    "data_source": "glue",
    "global_seed": 3,
    "loader_seed_base": 3044,
    "task_order": [
      "glue/rte",
      "glue/mrpc",
      "glue/cola"
    ],
    "tasks": {
      "glue/cola": {
        "num_labels": 2,
        "task": "glue/cola",
        "tokenizer_name": "microsoft/deberta-v3-base",
        "train_loader_shuffle_seed": 7301225,
        "train_size": 8551,
        "val_loader_shuffle_seed": 7301226,
        "val_size": 1043
      },
      "glue/mrpc": {
        "num_labels": 2,
        "task": "glue/mrpc",
        "tokenizer_name": "microsoft/deberta-v3-base",
        "train_loader_shuffle_seed": 7456854,
        "train_size": 3668,
        "val_loader_shuffle_seed": 7456855,
        "val_size": 408
      },
      "glue/rte": {
        "num_labels": 2,
        "task": "glue/rte",
        "tokenizer_name": "microsoft/deberta-v3-base",
        "train_loader_shuffle_seed": 6613181,
        "train_size": 2490,
        "val_loader_shuffle_seed": 6613182,
        "val_size": 277
      }
    }
  },
  "final_diagnostics": {
    "avg_intra_expert_coherence": 0.42613767861814483,
    "expert_diversity": [
      0.8713899608369428,
      0.9007292670826755,
      0.8344950665311897,
      0.8036478111353641
    ],
    "expert_names": [
      "e0",
      "e1",
      "e2",
      "e3"
    ],
    "expert_purity": [
      0.5536609292030334,
      0.45864608883857727,
      0.5208955407142639,
      0.5294851064682007
    ],
    "inter_expert_similarity": -0.05703707768098671,
    "inter_expert_similarity_matrix": [
      [
        1.0,
        -0.20060276543866445,
        -0.25202437298839336,
        0.23948222760669796
      ],
      [
        -0.20060276543866445,
        1.0,
        -0.03192748442065814,
        0.3008862395390942
      ],
      [
        -0.25202437298839336,
        -0.03192748442065814,
        1.0,
        -0.3980363103839965
      ],
      [
        0.23948222760669796,
        0.3008862395390942,
        -0.3980363103839965,
        1.0
      ]
    ],
    "intra_expert_coherence": [
      0.6938342017813168,
      0.6611188685162555,
      0.2716391627045369,
      0.07795848147047003
    ],
    "overall_task_conflict_cos": 0.49951000439328364,
    "task_conflict_matrix": [
      [
        1.0,
        0.5328584983069121,
        0.40963255227882334
      ],
      [
        0.5328584983069121,
        1.0,
        0.5560389625941154
      ],
      [
        0.40963255227882334,
        0.5560389625941154,
        1.0
      ]
    ],
    "task_grad_norm_cv": 0.45910786091855277,
    "task_grad_norms": [
      4.3438873291015625,
      10.702768325805664,
      15.942498207092285
    ],
    "task_names": [
      "glue/rte",
      "glue/mrpc",
      "glue/cola"
    ]
  },
  "final_step_metrics": {
    "alignment_reward": 0.10326363146305084,
    "avg_intra_expert_coherence": 0.42613767861814483,
    "expert_diversity_e0": 0.8713899608369428,
    "expert_diversity_e1": 0.9007292670826755,
    "expert_diversity_e2": 0.8344950665311897,
    "expert_diversity_e3": 0.8036478111353641,
    "expert_diversity_mean": 0.852565526396543,
    "expert_purity_e0": 0.5536609292030334,
    "expert_purity_e1": 0.45864608883857727,
    "expert_purity_e2": 0.5208955407142639,
    "expert_purity_e3": 0.5294851064682007,
    "expert_purity_mean": 0.5156719163060188,
    "inter_expert_similarity": -0.05703707768098671,
    "inter_expert_similarity_e0_e0": 1.0,
    "inter_expert_similarity_e0_e1": -0.20060276543866445,
    "inter_expert_similarity_e0_e2": -0.25202437298839336,
    "inter_expert_similarity_e0_e3": 0.23948222760669796,
    "inter_expert_similarity_e1_e0": -0.20060276543866445,
    "inter_expert_similarity_e1_e1": 1.0,
    "inter_expert_similarity_e1_e2": -0.03192748442065814,
    "inter_expert_similarity_e1_e3": 0.3008862395390942,
    "inter_expert_similarity_e2_e0": -0.25202437298839336,
    "inter_expert_similarity_e2_e1": -0.03192748442065814,
    "inter_expert_similarity_e2_e2": 1.0,
    "inter_expert_similarity_e2_e3": -0.3980363103839965,
    "inter_expert_similarity_e3_e0": 0.23948222760669796,
    "inter_expert_similarity_e3_e1": 0.3008862395390942,
    "inter_expert_similarity_e3_e2": -0.3980363103839965,
    "inter_expert_similarity_e3_e3": 1.0,
    "intra_expert_coherence_e0": 0.6938342017813168,
    "intra_expert_coherence_e1": 0.6611188685162555,
    "intra_expert_coherence_e2": 0.2716391627045369,
    "intra_expert_coherence_e3": 0.07795848147047003,
    "l_conflict": -0.10326363146305084,
    "l_conflict_e0": -0.03286270052194595,
    "l_conflict_e1": -0.026273634284734726,
    "l_conflict_e2": -0.010617570020258427,
    "l_conflict_e3": -0.03350973129272461,
    "load_cv": 0.11716090981234195,
    "load_max_min_ratio": 1.369086562481683,
    "overall_task_conflict_cos": 0.49951000439328364,
    "router_conflict_grad_l2": 0.0,
    "router_entropy": 1.3499806913788672,
    "router_load_e0": 0.2349894791841507,
    "router_load_e1": 0.29236480593681335,
    "router_load_e2": 0.21354734897613525,
    "router_load_e3": 0.25909847021102905,
    "step": 80.0,
    "task_acc__glue_cola": 0.7804410354745925,
    "task_acc__glue_mrpc": 0.7254901960784313,
    "task_acc__glue_rte": 0.6137184115523465,
    "task_conflict_t0_t0": 1.0,
    "task_conflict_t0_t1": 0.5328584983069121,
    "task_conflict_t0_t2": 0.40963255227882334,
    "task_conflict_t1_t0": 0.5328584983069121,
    "task_conflict_t1_t1": 1.0,
    "task_conflict_t1_t2": 0.5560389625941154,
    "task_conflict_t2_t0": 0.40963255227882334,
    "task_conflict_t2_t1": 0.5560389625941154,
    "task_conflict_t2_t2": 1.0,
    "task_grad_norm_cv": 0.45910786091855277,
    "task_loss__glue_cola": 0.5325027801565655,
    "task_loss__glue_mrpc": 0.5323764044864505,
    "task_loss__glue_rte": 0.6773855164221355,
    "train_acc": 0.706633288285956,
    "train_loss": 0.565391831068478,
    "train_step_loss": 0.7845335801442465,
    "utilization_ratio": 1.0,
    "val_acc": 0.7065498810351235,
    "val_loss": 0.5807549003550506
  },
  "final_val_acc": 0.7065498810351235,
  "method": "ours",
  "num_eval_points": 2,
  "overhead": {
    "mean_train_step_time_sec": 0.31335757770575584,
    "peak_cuda_memory_mb": 3752.11572265625,
    "wall_time_sec": 140.2596058230847
  },
  "reproducibility": {
    "command": "/share/home/yuli0398/Optimization/MOE-grad-conflict-routing/scripts/run.py --config configs/multitask_glue3_rte_mrpc_cola_real.yaml --set model.backbone_backend=hf --set model.hf_load_pretrained=true --set model.backbone=deberta --set model.hf_pretrained_name=microsoft/deberta-v3-base --set seed=3 --set method.name=ours --set train.steps=80 --set train.eval_every_steps=50 --set method.ours.use_load_norm=true --set method.ours.eps=1.744289893e-07 --set method.ours.lambda_align=0.005242072127 --set train.lr=2.699448611e-05 --out /share/home/yuli0398/Optimization/MOE-grad-conflict-routing/runs/paper_suite/multi_task/glue3_deberta/hpo/ours/trial_runs/coarse_043/ours_s3.json --curve_out /share/home/yuli0398/Optimization/MOE-grad-conflict-routing/runs/paper_suite/multi_task/glue3_deberta/hpo/ours/trial_runs/coarse_043/ours_s3_curve.csv",
    "curve_path": "/share/home/yuli0398/Optimization/MOE-grad-conflict-routing/runs/paper_suite/multi_task/glue3_deberta/hpo/ours/trial_runs/coarse_043/ours_s3_curve.csv",
    "cwd": "/share/home/yuli0398/Optimization/MOE-grad-conflict-routing",
    "runtime": {
      "cuda_available": true,
      "cuda_device_count": 1,
      "cuda_device_names": [
        "NVIDIA GeForce RTX 3090"
      ],
      "platform": "Linux-5.15.0-139-generic-x86_64-with-glibc2.31",
      "python_version": "3.10.18",
      "torch_version": "2.5.1+cu121"
    },
    "summary_path": "/share/home/yuli0398/Optimization/MOE-grad-conflict-routing/runs/paper_suite/multi_task/glue3_deberta/hpo/ours/trial_runs/coarse_043/ours_s3.json"
  },
  "resolved_config": {
    "data": {
      "datasets": [
        "glue/rte",
        "glue/mrpc",
        "glue/cola"
      ],
      "source": "glue",
      "train_size": 0,
      "val_size": 0
    },
    "method": {
      "baseline_cagrad": {
        "c": 0.4,
        "eps": 1e-08,
        "inner_lr": 0.1,
        "inner_steps": 10
      },
      "name": "ours",
      "ours": {
        "eps": 1.744289893e-07,
        "lambda_align": 0.005242072127,
        "micro_batch_size": 8,
        "use_load_norm": true
      }
    },
    "model": {
      "backbone": "deberta",
      "backbone_backend": "hf",
      "dropout": 0.1,
      "expert_type": "lora",
      "ffn_hidden_dim": 3072,
      "hf_load_pretrained": true,
      "hf_local_files_only": false,
      "hf_pretrained_name": "microsoft/deberta-v3-base",
      "hidden_dim": 768,
      "lora_alpha": 16.0,
      "lora_rank": 16,
      "max_seq_len": 128,
      "num_classes": 2,
      "num_experts": 4,
      "routing_mode": "softmax",
      "seq_len": 128,
      "top_k": 2,
      "vocab_size": 30522
    },
    "seed": 3,
    "train": {
      "batch_size": 8,
      "device_batch_size": 0,
      "eval_every_steps": 50,
      "eval_max_batches": 0,
      "grad_clip": 1.0,
      "log_every": 10,
      "lr": 2.699448611e-05,
      "micro_batch_size": 4,
      "steps": 80,
      "weight_decay": 0.01
    }
  },
  "resolved_config_sha256": "0afb0d2f647459de6219fafdd97c159c79d80b795e3869dbe865027d4bfaadb1",
  "seed": 3
}