{
  "batch_semantics": {
    "batch_hpo_semantics": "train.batch_size is the per-task effective batch size; total samples per update equals num_tasks * train.batch_size.",
    "configured_effective_batch_per_task": 8,
    "configured_effective_update_samples": 24,
    "device_transfer_semantics": "GPU staging chunks are only outer transport groups of whole logical micro-batches; they do not redefine vote partitioning or the effective update batch.",
    "gpu_streaming_chunk_size": 8,
    "logical_micro_batch_size": 4,
    "num_tasks_per_update": 3
  },
  "best_val_acc": 0.6845426627188239,
  "cli_overrides": [
    "model.backbone_backend=hf",
    "model.hf_load_pretrained=true",
    "model.backbone=deberta",
    "model.hf_pretrained_name=microsoft/deberta-v3-base",
    "seed=3",
    "method.name=ours",
    "train.steps=80",
    "train.eval_every_steps=50",
    "method.ours.use_load_norm=true",
    "method.ours.eps=1e-06",
    "method.ours.lambda_align=0.000130159178",
    "train.lr=4.8660544e-05"
  ],
  "config_path": "configs/multitask_glue3_rte_mrpc_cola_real.yaml",
  "config_path_resolved": "/share/home/yuli0398/Optimization/MOE-grad-conflict-routing/configs/multitask_glue3_rte_mrpc_cola_real.yaml",
  "data_reproducibility": {
    "data_source": "glue",
    "global_seed": 3,
    "loader_seed_base": 3044,
    "task_order": [
      "glue/rte",
      "glue/mrpc",
      "glue/cola"
    ],
    "tasks": {
      "glue/cola": {
        "num_labels": 2,
        "task": "glue/cola",
        "tokenizer_name": "microsoft/deberta-v3-base",
        "train_loader_shuffle_seed": 7301225,
        "train_size": 8551,
        "val_loader_shuffle_seed": 7301226,
        "val_size": 1043
      },
      "glue/mrpc": {
        "num_labels": 2,
        "task": "glue/mrpc",
        "tokenizer_name": "microsoft/deberta-v3-base",
        "train_loader_shuffle_seed": 7456854,
        "train_size": 3668,
        "val_loader_shuffle_seed": 7456855,
        "val_size": 408
      },
      "glue/rte": {
        "num_labels": 2,
        "task": "glue/rte",
        "tokenizer_name": "microsoft/deberta-v3-base",
        "train_loader_shuffle_seed": 6613181,
        "train_size": 2490,
        "val_loader_shuffle_seed": 6613182,
        "val_size": 277
      }
    }
  },
  "final_diagnostics": {
    "avg_intra_expert_coherence": 0.7465112852644179,
    "expert_diversity": [
      0.9940550105752842,
      0.968324387130489,
      0.9241591748457111,
      0.9769984856488207
    ],
    "expert_names": [
      "e0",
      "e1",
      "e2",
      "e3"
    ],
    "expert_purity": [
      0.36482560634613037,
      0.4605996906757355,
      0.4582970142364502,
      0.4227696359157562
    ],
    "inter_expert_similarity": -0.06198408996557462,
    "inter_expert_similarity_matrix": [
      [
        1.0,
        -0.07382802648525257,
        0.501788747192195,
        -0.12848858827511017
      ],
      [
        -0.07382802648525257,
        1.0,
        -0.3569467394436993,
        0.19113351498666134
      ],
      [
        0.501788747192195,
        -0.3569467394436993,
        1.0,
        -0.505563447768242
      ],
      [
        -0.12848858827511017,
        0.19113351498666134,
        -0.505563447768242,
        1.0
      ]
    ],
    "intra_expert_coherence": [
      0.8023755368179636,
      0.6314446321100452,
      0.789868239540768,
      0.7623567325888949
    ],
    "overall_task_conflict_cos": 0.5767395977519195,
    "task_conflict_matrix": [
      [
        1.0,
        0.6219506451348431,
        0.6060615916612722
      ],
      [
        0.6219506451348431,
        1.0,
        0.5022065564596432
      ],
      [
        0.6060615916612722,
        0.5022065564596432,
        1.0
      ]
    ],
    "task_grad_norm_cv": 0.1952155959674404,
    "task_grad_norms": [
      6.818851470947266,
      4.9603681564331055,
      8.114616394042969
    ],
    "task_names": [
      "glue/rte",
      "glue/mrpc",
      "glue/cola"
    ]
  },
  "final_step_metrics": {
    "alignment_reward": 0.04596477746963501,
    "avg_intra_expert_coherence": 0.7465112852644179,
    "expert_diversity_e0": 0.9940550105752842,
    "expert_diversity_e1": 0.968324387130489,
    "expert_diversity_e2": 0.9241591748457111,
    "expert_diversity_e3": 0.9769984856488207,
    "expert_diversity_mean": 0.9658842645500763,
    "expert_purity_e0": 0.36482560634613037,
    "expert_purity_e1": 0.4605996906757355,
    "expert_purity_e2": 0.4582970142364502,
    "expert_purity_e3": 0.4227696359157562,
    "expert_purity_mean": 0.42662298679351807,
    "inter_expert_similarity": -0.06198408996557462,
    "inter_expert_similarity_e0_e0": 1.0,
    "inter_expert_similarity_e0_e1": -0.07382802648525257,
    "inter_expert_similarity_e0_e2": 0.501788747192195,
    "inter_expert_similarity_e0_e3": -0.12848858827511017,
    "inter_expert_similarity_e1_e0": -0.07382802648525257,
    "inter_expert_similarity_e1_e1": 1.0,
    "inter_expert_similarity_e1_e2": -0.3569467394436993,
    "inter_expert_similarity_e1_e3": 0.19113351498666134,
    "inter_expert_similarity_e2_e0": 0.501788747192195,
    "inter_expert_similarity_e2_e1": -0.3569467394436993,
    "inter_expert_similarity_e2_e2": 1.0,
    "inter_expert_similarity_e2_e3": -0.505563447768242,
    "inter_expert_similarity_e3_e0": -0.12848858827511017,
    "inter_expert_similarity_e3_e1": 0.19113351498666134,
    "inter_expert_similarity_e3_e2": -0.505563447768242,
    "inter_expert_similarity_e3_e3": 1.0,
    "intra_expert_coherence_e0": 0.8023755368179636,
    "intra_expert_coherence_e1": 0.6314446321100452,
    "intra_expert_coherence_e2": 0.789868239540768,
    "intra_expert_coherence_e3": 0.7623567325888949,
    "l_conflict": -0.04596477746963501,
    "l_conflict_e0": -0.015855638310313225,
    "l_conflict_e1": -0.008254587650299072,
    "l_conflict_e2": -0.010762185789644718,
    "l_conflict_e3": -0.01109236478805542,
    "load_cv": 0.18896826374152467,
    "load_max_min_ratio": 1.5884273704238772,
    "overall_task_conflict_cos": 0.5767395977519195,
    "router_conflict_grad_l2": 0.0,
    "router_entropy": 1.3471536666016888,
    "router_load_e0": 0.27872124314308167,
    "router_load_e1": 0.19644924998283386,
    "router_load_e2": 0.2127840220928192,
    "router_load_e3": 0.3120453655719757,
    "step": 80.0,
    "task_acc__glue_cola": 0.7871524448705657,
    "task_acc__glue_mrpc": 0.696078431372549,
    "task_acc__glue_rte": 0.5703971119133574,
    "task_conflict_t0_t0": 1.0,
    "task_conflict_t0_t1": 0.6219506451348431,
    "task_conflict_t0_t2": 0.6060615916612722,
    "task_conflict_t1_t0": 0.6219506451348431,
    "task_conflict_t1_t1": 1.0,
    "task_conflict_t1_t2": 0.5022065564596432,
    "task_conflict_t2_t0": 0.6060615916612722,
    "task_conflict_t2_t1": 0.5022065564596432,
    "task_conflict_t2_t2": 1.0,
    "task_grad_norm_cv": 0.1952155959674404,
    "task_loss__glue_cola": 0.47930000720986426,
    "task_loss__glue_mrpc": 0.5600901143807991,
    "task_loss__glue_rte": 0.6889239720787321,
    "train_acc": 0.7037638999724467,
    "train_loss": 0.5539767714488546,
    "train_step_loss": 0.7268418023983638,
    "utilization_ratio": 1.0,
    "val_acc": 0.6845426627188239,
    "val_loss": 0.5761046978897986
  },
  "final_val_acc": 0.6845426627188239,
  "method": "ours",
  "num_eval_points": 2,
  "overhead": {
    "mean_train_step_time_sec": 0.30731125683523713,
    "peak_cuda_memory_mb": 3754.86572265625,
    "wall_time_sec": 137.38528283778578
  },
  "reproducibility": {
    "command": "/share/home/yuli0398/Optimization/MOE-grad-conflict-routing/scripts/run.py --config configs/multitask_glue3_rte_mrpc_cola_real.yaml --set model.backbone_backend=hf --set model.hf_load_pretrained=true --set model.backbone=deberta --set model.hf_pretrained_name=microsoft/deberta-v3-base --set seed=3 --set method.name=ours --set train.steps=80 --set train.eval_every_steps=50 --set method.ours.use_load_norm=true --set method.ours.eps=1e-06 --set method.ours.lambda_align=0.000130159178 --set train.lr=4.8660544e-05 --out /share/home/yuli0398/Optimization/MOE-grad-conflict-routing/runs/paper_suite/multi_task/glue3_deberta/hpo/ours/trial_runs/local_t3_076/ours_s3.json --curve_out /share/home/yuli0398/Optimization/MOE-grad-conflict-routing/runs/paper_suite/multi_task/glue3_deberta/hpo/ours/trial_runs/local_t3_076/ours_s3_curve.csv",
    "curve_path": "/share/home/yuli0398/Optimization/MOE-grad-conflict-routing/runs/paper_suite/multi_task/glue3_deberta/hpo/ours/trial_runs/local_t3_076/ours_s3_curve.csv",
    "cwd": "/share/home/yuli0398/Optimization/MOE-grad-conflict-routing",
    "runtime": {
      "cuda_available": true,
      "cuda_device_count": 1,
      "cuda_device_names": [
        "NVIDIA GeForce RTX 3090"
      ],
      "platform": "Linux-5.15.0-139-generic-x86_64-with-glibc2.31",
      "python_version": "3.10.18",
      "torch_version": "2.5.1+cu121"
    },
    "summary_path": "/share/home/yuli0398/Optimization/MOE-grad-conflict-routing/runs/paper_suite/multi_task/glue3_deberta/hpo/ours/trial_runs/local_t3_076/ours_s3.json"
  },
  "resolved_config": {
    "data": {
      "datasets": [
        "glue/rte",
        "glue/mrpc",
        "glue/cola"
      ],
      "source": "glue",
      "train_size": 0,
      "val_size": 0
    },
    "method": {
      "baseline_cagrad": {
        "c": 0.4,
        "eps": 1e-08,
        "inner_lr": 0.1,
        "inner_steps": 10
      },
      "name": "ours",
      "ours": {
        "eps": 1e-06,
        "lambda_align": 0.000130159178,
        "micro_batch_size": 8,
        "use_load_norm": true
      }
    },
    "model": {
      "backbone": "deberta",
      "backbone_backend": "hf",
      "dropout": 0.1,
      "expert_type": "lora",
      "ffn_hidden_dim": 3072,
      "hf_load_pretrained": true,
      "hf_local_files_only": false,
      "hf_pretrained_name": "microsoft/deberta-v3-base",
      "hidden_dim": 768,
      "lora_alpha": 16.0,
      "lora_rank": 16,
      "max_seq_len": 128,
      "num_classes": 2,
      "num_experts": 4,
      "routing_mode": "softmax",
      "seq_len": 128,
      "top_k": 2,
      "vocab_size": 30522
    },
    "seed": 3,
    "train": {
      "batch_size": 8,
      "device_batch_size": 0,
      "eval_every_steps": 50,
      "eval_max_batches": 0,
      "grad_clip": 1.0,
      "log_every": 10,
      "lr": 4.8660544e-05,
      "micro_batch_size": 4,
      "steps": 80,
      "weight_decay": 0.01
    }
  },
  "resolved_config_sha256": "5251df8fac05c4ad5c9389a3765610b80df68f3d27991e7cbbd7302f8e97c443",
  "seed": 3
}